{"nodes": [{"id": "trip", "label": "trip.go", "file_type": "code", "source_file": "services/trip-service/internal/http-server/dto/response/trip.go", "source_location": "L1"}, {"id": "response_trip", "label": "Trip", "file_type": "code", "source_file": "services/trip-service/internal/http-server/dto/response/trip.go", "source_location": "L14"}, {"id": "response_listtrips", "label": "ListTrips", "file_type": "code", "source_file": "services/trip-service/internal/http-server/dto/response/trip.go", "source_location": "L33"}, {"id": "response_itineraryversionsummary", "label": "ItineraryVersionSummary", "file_type": "code", "source_file": "services/trip-service/internal/http-server/dto/response/trip.go", "source_location": "L40"}, {"id": "response_itineraryversiondetail", "label": "ItineraryVersionDetail", "file_type": "code", "source_file": "services/trip-service/internal/http-server/dto/response/trip.go", "source_location": "L50"}, {"id": "response_listitineraryversions", "label": "ListItineraryVersions", "file_type": "code", "source_file": "services/trip-service/internal/http-server/dto/response/trip.go", "source_location": "L62"}, {"id": "trip_newlisttrips", "label": "NewListTrips()", "file_type": "code", "source_file": "services/trip-service/internal/http-server/dto/response/trip.go", "source_location": "L70"}, {"id": "trip_newlistitineraryversions", "label": "NewListItineraryVersions()", "file_type": "code", "source_file": "services/trip-service/internal/http-server/dto/response/trip.go", "source_location": "L80"}, {"id": "trip_newitineraryversionsummary", "label": "NewItineraryVersionSummary()", "file_type": "code", "source_file": "services/trip-service/internal/http-server/dto/response/trip.go", "source_location": "L89"}, {"id": "trip_newitineraryversiondetail", "label": "NewItineraryVersionDetail()", "file_type": "code", "source_file": "services/trip-service/internal/http-server/dto/response/trip.go", "source_location": "L101"}, {"id": "trip_newtrip", "label": "NewTrip()", "file_type": "code", "source_file": "services/trip-service/internal/http-server/dto/response/trip.go", "source_location": "L114"}, {"id": "trip_metadataorempty", "label": "metadataOrEmpty()", "file_type": "code", "source_file": "services/trip-service/internal/http-server/dto/response/trip.go", "source_location": "L144"}], "edges": [{"source": "trip", "target": "time", "relation": "imports_from", "confidence": "EXTRACTED", "source_file": "services/trip-service/internal/http-server/dto/response/trip.go", "source_location": "L6", "weight": 1.0}, {"source": "trip", "target": "uuid", "relation": "imports_from", "confidence": "EXTRACTED", "source_file": "services/trip-service/internal/http-server/dto/response/trip.go", "source_location": "L8", "weight": 1.0}, {"source": "trip", "target": "entity", "relation": "imports_from", "confidence": "EXTRACTED", "source_file": "services/trip-service/internal/http-server/dto/response/trip.go", "source_location": "L10", "weight": 1.0}, {"source": "trip", "target": "response_trip", "relation": "contains", "confidence": "EXTRACTED", "source_file": "services/trip-service/internal/http-server/dto/response/trip.go", "source_location": "L14", "weight": 1.0}, {"source": "trip", "target": "response_listtrips", "relation": "contains", "confidence": "EXTRACTED", "source_file": "services/trip-service/internal/http-server/dto/response/trip.go", "source_location": "L33", "weight": 1.0}, {"source": "trip", "target": "response_itineraryversionsummary", "relation": "contains", "confidence": "EXTRACTED", "source_file": "services/trip-service/internal/http-server/dto/response/trip.go", "source_location": "L40", "weight": 1.0}, {"source": "trip", "target": "response_itineraryversiondetail", "relation": "contains", "confidence": "EXTRACTED", "source_file": "services/trip-service/internal/http-server/dto/response/trip.go", "source_location": "L50", "weight": 1.0}, {"source": "trip", "target": "response_listitineraryversions", "relation": "contains", "confidence": "EXTRACTED", "source_file": "services/trip-service/internal/http-server/dto/response/trip.go", "source_location": "L62", "weight": 1.0}, {"source": "trip", "target": "trip_newlisttrips", "relation": "contains", "confidence": "EXTRACTED", "source_file": "services/trip-service/internal/http-server/dto/response/trip.go", "source_location": "L70", "weight": 1.0}, {"source": "trip", "target": "trip_newlistitineraryversions", "relation": "contains", "confidence": "EXTRACTED", "source_file": "services/trip-service/internal/http-server/dto/response/trip.go", "source_location": "L80", "weight": 1.0}, {"source": "trip", "target": "trip_newitineraryversionsummary", "relation": "contains", "confidence": "EXTRACTED", "source_file": "services/trip-service/internal/http-server/dto/response/trip.go", "source_location": "L89", "weight": 1.0}, {"source": "trip", "target": "trip_newitineraryversiondetail", "relation": "contains", "confidence": "EXTRACTED", "source_file": "services/trip-service/internal/http-server/dto/response/trip.go", "source_location": "L101", "weight": 1.0}, {"source": "trip", "target": "trip_newtrip", "relation": "contains", "confidence": "EXTRACTED", "source_file": "services/trip-service/internal/http-server/dto/response/trip.go", "source_location": "L114", "weight": 1.0}, {"source": "trip", "target": "trip_metadataorempty", "relation": "contains", "confidence": "EXTRACTED", "source_file": "services/trip-service/internal/http-server/dto/response/trip.go", "source_location": "L144", "weight": 1.0}, {"source": "trip_newlisttrips", "target": "trip_newtrip", "relation": "calls", "confidence": "EXTRACTED", "source_file": "services/trip-service/internal/http-server/dto/response/trip.go", "source_location": "L73", "weight": 1.0}, {"source": "trip_newlistitineraryversions", "target": "trip_newitineraryversionsummary", "relation": "calls", "confidence": "EXTRACTED", "source_file": "services/trip-service/internal/http-server/dto/response/trip.go", "source_location": "L83", "weight": 1.0}, {"source": "trip_newitineraryversionsummary", "target": "trip_metadataorempty", "relation": "calls", "confidence": "EXTRACTED", "source_file": "services/trip-service/internal/http-server/dto/response/trip.go", "source_location": "L95", "weight": 1.0}, {"source": "trip_newitineraryversiondetail", "target": "trip_metadataorempty", "relation": "calls", "confidence": "EXTRACTED", "source_file": "services/trip-service/internal/http-server/dto/response/trip.go", "source_location": "L108", "weight": 1.0}]}